Metadata-Version: 1.1
Name: django-test-query-counter
Version: 0.1.0
Summary: A Django Toolkit for controlling Query count when testing
Home-page: https://github.com/sophilabs/django-request-query-count
Author: Ignacio Avas
Author-email: iavas@sophilabs.com
License: MIT
Keywords: django-test-query-counter
Platform: UNKNOWN
Classifier: Development Status :: 3 - Alpha
Classifier: Framework :: Django
Classifier: Framework :: Django :: 1.8
Classifier: Framework :: Django :: 1.9
Classifier: Framework :: Django :: 1.10
Classifier: Intended Audience :: Developers
Classifier: License :: OSI Approved :: BSD License
Classifier: Natural Language :: English
Classifier: Programming Language :: Python :: 2
Classifier: Programming Language :: Python :: 2.7
Classifier: Programming Language :: Python :: 3
Classifier: Programming Language :: Python :: 3.3
Classifier: Programming Language :: Python :: 3.4
Classifier: Programming Language :: Python :: 3.5
